fortrex/__init__.py
fortrex/install-poetry.py
fortrex/main.py
fortrex-0.1.0.dist-info/entry_points.txt
fortrex-0.1.0.dist-info/LICENSE
fortrex-0.1.0.dist-info/METADATA
fortrex-0.1.0.dist-info/WHEEL
fortrex-0.1.0.dist-info/RECORD
